{
  "ghi_chu": "Vua/chúa bổ sung — nhà Trần (An Sinh, Đông Triều), nhà Lê sơ (Lam Kinh), nhà Mạc (Dương Kinh), chúa Nguyễn và chúa Trịnh — chưa có trong CSDL. Toạ độ khu lăng mộ/di tích qua OpenStreetMap Nominatim đối chiếu địa danh trong nguồn; nội dung theo cổng di sản/nhà nước (dsvh.gov.vn — Cục Di sản văn hoá, ditichlamkinh.vn — Khu di tích Lam Kinh, haiphong.gov.vn — UBND TP Hải Phòng, thanhuyhue.vn — Tỉnh uỷ Thừa Thiên Huế, hueworldheritage.org.vn — Trung tâm BTDT Cố đô Huế, scov.gov.vn — Sở VHTTDL Thừa Thiên Huế). KHÔNG dùng Wikipedia. WebSearch không khả dụng trong phiên này — tra cứu qua WebFetch DuckDuckGo Lite và crawl Google (web-crawl skill) rồi fetch trực tiếp cổng nhà nước.",
  "ngay_cap_nhat": "2026-07-20",
  "sources": [
    "Cục Di sản văn hoá — dsvh.gov.vn",
    "Khu di tích Lam Kinh — ditichlamkinh.vn",
    "UBND thành phố Hải Phòng — haiphong.gov.vn",
    "Tỉnh uỷ Thừa Thiên Huế — thanhuyhue.vn",
    "Trung tâm Bảo tồn Di tích Cố đô Huế — hueworldheritage.org.vn",
    "Sở Văn hoá, Thể thao và Du lịch Thừa Thiên Huế — scov.gov.vn",
    "OpenStreetMap Nominatim (toạ độ)"
  ],
  "items": [
    {
      "id": "tran-thai-tong",
      "ten": "Trần Thái Tông",
      "lon": 106.4832, "lat": 21.0975,
      "loai": "vua-chua",
      "nam_hien_thi": "1218–1277, trị vì 1226–1258",
      "mo_ta": "Tên thật Trần Cảnh, vị vua đầu tiên sáng lập nhà Trần, lên ngôi khi nhà Lý suy vi. Cùng hoàng tộc lãnh đạo quân dân Đại Việt đánh bại cuộc xâm lược lần thứ nhất của quân Mông Cổ (1258). An táng tại lăng Tư Phúc trong khu di tích nhà Trần ở Đông Triều.",
      "dia_diem": "Lăng Tư Phúc, thôn Trại Lốc, xã An Sinh, thị xã Đông Triều, Quảng Ninh — Khu di tích lịch sử nhà Trần",
      "do_tin_cay_toa_do": "trung",
      "trang_thai": "draft",
      "nguon": ["Cục Di sản văn hoá — dsvh.gov.vn (Khu di tích lịch sử nhà Trần tại Đông Triều) — https://dsvh.gov.vn/khu-di-tich-lich-su-nha-tran-tai-dong-trieu-2972"]
    },
    {
      "id": "tran-thanh-tong",
      "ten": "Trần Thánh Tông",
      "lon": 106.4836, "lat": 21.0978,
      "loai": "vua-chua",
      "nam_hien_thi": "1240–1290, trị vì 1258–1278",
      "mo_ta": "Tên thật Trần Hoảng, con trưởng vua Trần Thái Tông. Với cương vị Thái thượng hoàng, cùng vua Trần Nhân Tông chỉ đạo kháng chiến chống Mông Nguyên lần thứ hai (1285) thắng lợi. An táng tại lăng Tư Phúc, nơi thờ chung nhiều vị vua đầu triều Trần.",
      "dia_diem": "Lăng Tư Phúc, thôn Trại Lốc, xã An Sinh, thị xã Đông Triều, Quảng Ninh — Khu di tích lịch sử nhà Trần",
      "do_tin_cay_toa_do": "trung",
      "trang_thai": "draft",
      "nguon": ["Cục Di sản văn hoá — dsvh.gov.vn (Khu di tích lịch sử nhà Trần tại Đông Triều) — https://dsvh.gov.vn/khu-di-tich-lich-su-nha-tran-tai-dong-trieu-2972"]
    },
    {
      "id": "tran-anh-tong",
      "ten": "Trần Anh Tông",
      "lon": 106.4865, "lat": 21.0995,
      "loai": "vua-chua",
      "nam_hien_thi": "1276–1320, trị vì 1293–1314",
      "mo_ta": "Tên thật Trần Thuyên, con trưởng vua Trần Nhân Tông. Trị vì trong giai đoạn thái bình sau kháng chiến chống Mông Nguyên, chú trọng phát triển kinh tế và Nho học. An táng tại Thái Lăng, Đông Triều.",
      "dia_diem": "Thái Lăng, xã An Sinh, thị xã Đông Triều, Quảng Ninh — Khu di tích lịch sử nhà Trần",
      "do_tin_cay_toa_do": "trung",
      "trang_thai": "draft",
      "nguon": ["Cục Di sản văn hoá — dsvh.gov.vn (Khu di tích lịch sử nhà Trần tại Đông Triều) — https://dsvh.gov.vn/khu-di-tich-lich-su-nha-tran-tai-dong-trieu-2972"]
    },
    {
      "id": "tran-minh-tong",
      "ten": "Trần Minh Tông",
      "lon": 106.4855, "lat": 21.1005,
      "loai": "vua-chua",
      "nam_hien_thi": "1300–1357, trị vì 1314–1329",
      "mo_ta": "Tên thật Trần Mạnh, con vua Trần Anh Tông. Thời kỳ trị vì được sử sách đánh giá là thịnh trị, trọng dụng nhiều danh thần như Trương Hán Siêu, Nguyễn Trung Ngạn. An táng tại Mục Lăng, Đông Triều.",
      "dia_diem": "Mục Lăng, xã An Sinh, thị xã Đông Triều, Quảng Ninh — Khu di tích lịch sử nhà Trần",
      "do_tin_cay_toa_do": "trung",
      "trang_thai": "draft",
      "nguon": ["Cục Di sản văn hoá — dsvh.gov.vn (Khu di tích lịch sử nhà Trần tại Đông Triều) — https://dsvh.gov.vn/khu-di-tich-lich-su-nha-tran-tai-dong-trieu-2972"]
    },
    {
      "id": "tran-du-tong",
      "ten": "Trần Dụ Tông",
      "lon": 106.4870, "lat": 21.1015,
      "loai": "vua-chua",
      "nam_hien_thi": "1336–1369, trị vì 1341–1369",
      "mo_ta": "Tên thật Trần Hạo, con vua Trần Minh Tông, lên ngôi khi còn nhỏ tuổi. Cuối đời triều chính suy yếu, là giai đoạn bản lề trước khi nhà Trần suy vong. An táng tại Phụ Sơn Lăng, Đông Triều.",
      "dia_diem": "Phụ Sơn Lăng, xã An Sinh, thị xã Đông Triều, Quảng Ninh — Khu di tích lịch sử nhà Trần",
      "do_tin_cay_toa_do": "trung",
      "trang_thai": "draft",
      "nguon": ["Cục Di sản văn hoá — dsvh.gov.vn (Khu di tích lịch sử nhà Trần tại Đông Triều) — https://dsvh.gov.vn/khu-di-tich-lich-su-nha-tran-tai-dong-trieu-2972"]
    },
    {
      "id": "le-thai-tong",
      "ten": "Lê Thái Tông",
      "lon": 105.5278, "lat": 19.9335,
      "loai": "vua-chua",
      "nam_hien_thi": "1423–1442, trị vì 1433–1442",
      "mo_ta": "Tên thật Lê Nguyên Long, con thứ vua Lê Thái Tổ (Lê Lợi), lên ngôi năm 11 tuổi. Cho khởi dựng các miếu điện thờ tổ tiên tại Lam Kinh sau khi vua cha băng hà. An táng tại khu lăng tẩm Lam Kinh, quê hương nhà Lê sơ.",
      "dia_diem": "Khu di tích Lam Kinh, thị trấn Lam Sơn, huyện Thọ Xuân, Thanh Hóa",
      "do_tin_cay_toa_do": "trung",
      "trang_thai": "draft",
      "nguon": ["Khu di tích Lam Kinh — ditichlamkinh.vn (Các vua Lê sơ về Lam Kinh bái yết sơn lăng) — https://ditichlamkinh.vn/vi/cac-vua-le-so-ve-lam-kinh-bai-yet-son-lang-071C5589669A538F8991C4C2D18C8BE3.html"]
    },
    {
      "id": "le-nhan-tong",
      "ten": "Lê Nhân Tông",
      "lon": 105.5298, "lat": 19.9355,
      "loai": "vua-chua",
      "nam_hien_thi": "1441–1459, trị vì 1442–1459",
      "mo_ta": "Tên thật Lê Bang Cơ, lên ngôi khi mới 2 tuổi, mẫu hậu Nguyễn Thị Anh nhiếp chính. Từng về Lam Kinh bái yết sơn lăng tổ tiên năm 1448 và cho đặt tên các điện thờ chính (điện Quang Đức, điện Diên Khánh). An táng tại khu lăng tẩm Lam Kinh.",
      "dia_diem": "Khu di tích Lam Kinh, thị trấn Lam Sơn, huyện Thọ Xuân, Thanh Hóa",
      "do_tin_cay_toa_do": "trung",
      "trang_thai": "draft",
      "nguon": ["Khu di tích Lam Kinh — ditichlamkinh.vn (Các vua Lê sơ về Lam Kinh bái yết sơn lăng) — https://ditichlamkinh.vn/vi/cac-vua-le-so-ve-lam-kinh-bai-yet-son-lang-071C5589669A538F8991C4C2D18C8BE3.html"]
    },
    {
      "id": "le-hien-tong",
      "ten": "Lê Hiến Tông",
      "lon": 105.5288, "lat": 19.9365,
      "loai": "vua-chua",
      "nam_hien_thi": "1461–1504, trị vì 1497–1504",
      "mo_ta": "Tên thật Lê Tranh, con trưởng vua Lê Thánh Tông, kế nghiệp giữ vững cơ nghiệp thịnh trị nhà Lê sơ. Từng về Lam Kinh bái yết sơn lăng tổ tiên năm 1504. An táng tại khu lăng tẩm Lam Kinh.",
      "dia_diem": "Khu di tích Lam Kinh, thị trấn Lam Sơn, huyện Thọ Xuân, Thanh Hóa",
      "do_tin_cay_toa_do": "trung",
      "trang_thai": "draft",
      "nguon": ["Khu di tích Lam Kinh — ditichlamkinh.vn (Các vua Lê sơ về Lam Kinh bái yết sơn lăng) — https://ditichlamkinh.vn/vi/cac-vua-le-so-ve-lam-kinh-bai-yet-son-lang-071C5589669A538F8991C4C2D18C8BE3.html"]
    },
    {
      "id": "mac-dang-dung",
      "ten": "Mạc Đăng Dung",
      "lon": 106.6687, "lat": 20.7508,
      "loai": "vua-chua",
      "nam_hien_thi": "1483–1541, làm vua 1527–1529",
      "mo_ta": "Người làng Cổ Trai (nay xã Ngũ Đoan, Kiến Thụy, Hải Phòng), từ một võ tướng nhà Lê lên ngôi lập ra nhà Mạc năm 1527, đến 1529 nhường ngôi cho con Mạc Đăng Doanh song vẫn giữ thực quyền với danh vị Thái thượng hoàng. Quê hương ông — vùng Dương Kinh xưa — nay là Cụm di tích quốc gia đặc biệt liên quan nhà Mạc.",
      "dia_diem": "Khu tưởng niệm Vương triều Mạc, xã Ngũ Đoan (Dương Kinh xưa), huyện Kiến Thụy, Hải Phòng",
      "do_tin_cay_toa_do": "trung",
      "trang_thai": "draft",
      "nguon": ["UBND thành phố Hải Phòng — haiphong.gov.vn (Khu tưởng niệm Vương triều Mạc) — https://haiphong.gov.vn/di-tich-danh-thang/khu-tuong-niem-vuong-trieu-mac-626648"]
    },
    {
      "id": "nguyen-phuc-nguyen",
      "ten": "Nguyễn Phúc Nguyên — Chúa Sãi",
      "lon": 107.5607, "lat": 16.3547,
      "loai": "vua-chua",
      "nam_hien_thi": "1563–1635, ở ngôi chúa 1613–1635",
      "mo_ta": "Con thứ sáu của chúa Tiên Nguyễn Hoàng, tục gọi chúa Sãi, là chúa Nguyễn thứ hai ở Đàng Trong. Tiếp tục sự nghiệp mở mang bờ cõi phương Nam, củng cố phòng tuyến chống lại các cuộc tấn công của chúa Trịnh. An táng tại lăng Trường Diễn.",
      "dia_diem": "Lăng Trường Diễn, thôn Hải Cát, xã Hương Thọ, thành phố Huế",
      "do_tin_cay_toa_do": "cao",
      "trang_thai": "draft",
      "nguon": ["Tỉnh uỷ Thừa Thiên Huế — thanhuyhue.vn (4 lăng mộ của vua, chúa Nguyễn được xếp hạng di tích lịch sử cấp tỉnh) — https://thanhuyhue.vn/tin-tuc-trong-tinh/van-hoa-du-lich/4-lang-mo-cua-vuachua-nguyen-duoc-xep-hang-di-tich-lich-su-cap-tinh.html"]
    },
    {
      "id": "nguyen-phuc-chu",
      "ten": "Nguyễn Phúc Chu — Chúa Minh",
      "lon": 107.5446, "lat": 16.4537,
      "loai": "vua-chua",
      "nam_hien_thi": "ở ngôi chúa 1691–1725",
      "mo_ta": "Chúa Nguyễn thứ sáu ở Đàng Trong, tục gọi chúa Minh, nổi tiếng sùng mộ đạo Phật. Cho đại trùng kiến chùa Thiên Mụ và dựng bia «Ngự kiến Thiên Mụ tự» năm 1715 (nay là Bảo vật quốc gia, công nhận 2020). Thời ông, vùng đất Đàng Trong tiếp tục được mở mang.",
      "dia_diem": "Chùa Thiên Mụ, phường Kim Long, thành phố Huế",
      "do_tin_cay_toa_do": "cao",
      "trang_thai": "draft",
      "nguon": ["Trung tâm Bảo tồn Di tích Cố đô Huế — hueworldheritage.org.vn (Bia «Ngự kiến Thiên Mụ Tự» của chúa Nguyễn Phúc Chu) — http://hueworldheritage.org.vn/tabid/48/language/vi-VN/Default.aspx/tid/Bia-%E2%80%9CNgu-kien-Thien-Mu-Tu%E2%80%9D-cua-chua-Nguyen-Phuc-Chu.html/pid/507/cid/126"]
    },
    {
      "id": "trinh-kiem",
      "ten": "Trịnh Kiểm",
      "lon": 105.6480, "lat": 20.0399,
      "loai": "vua-chua",
      "nam_hien_thi": "trị vì 1545–1570 (chúa Trịnh đầu tiên)",
      "mo_ta": "Tước hiệu Thế Tổ Minh Khang Thái Vương, người đặt nền móng cơ nghiệp họ Trịnh ở Đàng Ngoài, phò tá nhà Lê thời Trung hưng chống lại nhà Mạc. Được thờ tại quần thể Phủ Trịnh — Nghè Vẹt cùng các đời chúa Trịnh.",
      "dia_diem": "Phủ Trịnh — Nghè Vẹt, xã Vĩnh Lộc (Vĩnh Hùng cũ), tỉnh Thanh Hóa",
      "do_tin_cay_toa_do": "trung",
      "trang_thai": "draft",
      "nguon": [
        "Sở VHTTDL Thừa Thiên Huế — scov.gov.vn (Thời kỳ Trịnh - Nguyễn phân tranh, phần 1) — https://scov.gov.vn/dat-nuoc-con-nguoi/tom-tat-bien-nien-su-vn/thoi-ky-trinh-nguyen-phan-tranh-phan-1-.html",
        "Cục Di sản văn hoá — dsvh.gov.vn (Mùa xuân nghĩ về di sản văn hóa xứ Thanh, nhắc Phủ Trịnh - Nghè Vẹt tại Vĩnh Lộc) — http://dsvh.gov.vn/Upload/files/Tap%20chi%20DSVH/So%2034/3417_Mua%20Xuan%20nghi%20ve%20Di%20san%20van%20hoa%20xu%20Thanh.pdf"
      ]
    },
    {
      "id": "trinh-tung",
      "ten": "Trịnh Tùng",
      "lon": 105.6500, "lat": 20.0419,
      "loai": "vua-chua",
      "nam_hien_thi": "trị vì 1570–1623 (53 năm)",
      "mo_ta": "Tước hiệu Bình An Vương, con Trịnh Kiểm, là người đầu tiên trong dòng họ chính thức xưng chúa. Có công đánh dẹp dư đảng nhà Mạc, khôi phục kinh thành Thăng Long cho vua Lê năm 1593, mở đầu thời kỳ vua Lê – chúa Trịnh song song trị vì.",
      "dia_diem": "Phủ Trịnh — Nghè Vẹt, xã Vĩnh Lộc (Vĩnh Hùng cũ), tỉnh Thanh Hóa",
      "do_tin_cay_toa_do": "trung",
      "trang_thai": "draft",
      "nguon": [
        "Sở VHTTDL Thừa Thiên Huế — scov.gov.vn (Thời kỳ Trịnh - Nguyễn phân tranh, phần 1) — https://scov.gov.vn/dat-nuoc-con-nguoi/tom-tat-bien-nien-su-vn/thoi-ky-trinh-nguyen-phan-tranh-phan-1-.html",
        "Cục Di sản văn hoá — dsvh.gov.vn (Mùa xuân nghĩ về di sản văn hóa xứ Thanh, nhắc Phủ Trịnh - Nghè Vẹt tại Vĩnh Lộc) — http://dsvh.gov.vn/Upload/files/Tap%20chi%20DSVH/So%2034/3417_Mua%20Xuan%20nghi%20ve%20Di%20san%20van%20hoa%20xu%20Thanh.pdf"
      ]
    },
    {
      "id": "trinh-cuong",
      "ten": "Trịnh Cương",
      "lon": 105.6510, "lat": 20.0429,
      "loai": "vua-chua",
      "nam_hien_thi": "trị vì 1709–1729",
      "mo_ta": "Tước hiệu An Đô Vương, đời chúa thứ sáu họ Trịnh. Thời ông, Đàng Ngoài tương đối ổn định, chú trọng chỉnh đốn quan chế, thuế khoá và thi cử.",
      "dia_diem": "Phủ Trịnh — Nghè Vẹt, xã Vĩnh Lộc (Vĩnh Hùng cũ), tỉnh Thanh Hóa",
      "do_tin_cay_toa_do": "trung",
      "trang_thai": "draft",
      "nguon": [
        "Sở VHTTDL Thừa Thiên Huế — scov.gov.vn (Thời kỳ Trịnh - Nguyễn phân tranh, phần 1) — https://scov.gov.vn/dat-nuoc-con-nguoi/tom-tat-bien-nien-su-vn/thoi-ky-trinh-nguyen-phan-tranh-phan-1-.html",
        "Cục Di sản văn hoá — dsvh.gov.vn (Mùa xuân nghĩ về di sản văn hóa xứ Thanh, nhắc Phủ Trịnh - Nghè Vẹt tại Vĩnh Lộc) — http://dsvh.gov.vn/Upload/files/Tap%20chi%20DSVH/So%2034/3417_Mua%20Xuan%20nghi%20ve%20Di%20san%20van%20hoa%20xu%20Thanh.pdf"
      ]
    }
  ]
}
