{
  "ghi_chu": "Tác phẩm của Chủ tịch Hồ Chí Minh (1890–1969) — đã hết thời hạn bảo hộ bản quyền tại Việt Nam, đăng toàn văn. Bản dịch của Nam Trân (mất 1967) cũng đã thuộc public domain; bản dịch của dịch giả mất sau 1976 vẫn còn bảo hộ và chỉ được dẫn nguồn.",
  "items": [
    {
      "id": "canh-khuya",
      "ten": "Cảnh khuya",
      "tac_gia": "Hồ Chí Minh",
      "thoi_ky": "1947 — chiến khu Việt Bắc, kháng chiến chống Pháp",
      "the_loai": "Thất ngôn tứ tuyệt (tiếng Việt)",
      "ban_quyen": "public-domain",
      "lien_quan_tinh": ["thai-nguyen", "tuyen-quang"],
      "loi_binh": "Thi sĩ và chiến sĩ trong cùng một câu thơ: say cảnh trăng rừng mà vẫn «lo nỗi nước nhà».",
      "nguyen_van": [
        "Tiếng suối trong như tiếng hát xa,",
        "Trăng lồng cổ thụ, bóng lồng hoa.",
        "Cảnh khuya như vẽ, người chưa ngủ,",
        "Chưa ngủ vì lo nỗi nước nhà."
      ],
      "sources": ["Hồ Chí Minh — Thơ, NXB Văn học", "SGK Ngữ văn — NXB Giáo dục Việt Nam"]
    },
    {
      "id": "nguyen-tieu",
      "ten": "Nguyên tiêu (Rằm tháng Giêng)",
      "tac_gia": "Hồ Chí Minh",
      "thoi_ky": "1948 — họp bàn việc quân trên sông ở Việt Bắc",
      "the_loai": "Thất ngôn tứ tuyệt chữ Hán",
      "ban_quyen": "public-domain",
      "lien_quan_tinh": ["thai-nguyen", "tuyen-quang"],
      "loi_binh": "Ba chữ «xuân» trong một câu — sức xuân của đất trời hoà vào việc quân việc nước; «trăng đầy thuyền» thành hình ảnh kinh điển.",
      "nguyen_van": [
        "Kim dạ nguyên tiêu nguyệt chính viên,",
        "Xuân giang, xuân thủy tiếp xuân thiên.",
        "Yên ba thâm xứ đàm quân sự,",
        "Dạ bán quy lai nguyệt mãn thuyền."
      ],
      "ban_dich": [
        "(Dịch nghĩa) Đêm nay rằm tháng Giêng, trăng vừa tròn đầy;",
        "sông xuân, nước xuân nối liền trời xuân.",
        "Nơi khói sóng thăm thẳm bàn việc quân;",
        "nửa đêm trở về, ánh trăng đầy thuyền."
      ],
      "ghi_chu_dich": "Bản dịch thơ lục bát quen thuộc của Xuân Thủy (1912–1985) còn thời hạn bảo hộ — xin xem tại nguồn dẫn; trên đây là dịch nghĩa văn xuôi.",
      "sources": ["Hồ Chí Minh — Thơ, NXB Văn học", "SGK Ngữ văn — NXB Giáo dục Việt Nam"]
    },
    {
      "id": "tuc-canh-pac-bo",
      "ten": "Tức cảnh Pác Bó",
      "tac_gia": "Hồ Chí Minh",
      "thoi_ky": "02/1941 — hang Pác Bó, Cao Bằng, sau 30 năm bôn ba trở về Tổ quốc",
      "the_loai": "Thất ngôn tứ tuyệt (tiếng Việt)",
      "ban_quyen": "public-domain",
      "lien_quan_tinh": ["cao-bang"],
      "loi_binh": "«Cuộc đời cách mạng thật là sang» — cái «sang» của người coi gian khổ là lẽ thường khi được sống giữa lòng Tổ quốc.",
      "nguyen_van": [
        "Sáng ra bờ suối, tối vào hang,",
        "Cháo bẹ, rau măng vẫn sẵn sàng.",
        "Bàn đá chông chênh dịch sử Đảng,",
        "Cuộc đời cách mạng thật là sang."
      ],
      "sources": ["Hồ Chí Minh — Thơ, NXB Văn học", "Khu di tích quốc gia đặc biệt Pác Bó — Cao Bằng", "SGK Ngữ văn — NXB Giáo dục Việt Nam"]
    },
    {
      "id": "ngam-trang",
      "ten": "Ngắm trăng (Vọng nguyệt — Nhật ký trong tù)",
      "tac_gia": "Hồ Chí Minh",
      "thoi_ky": "1942–1943 — trong nhà lao Tưởng Giới Thạch, Quảng Tây",
      "the_loai": "Thất ngôn tứ tuyệt chữ Hán; bản dịch Nam Trân",
      "ban_quyen": "public-domain",
      "lien_quan_tinh": [],
      "loi_binh": "Song sắt nhà tù bất lực trước một cuộc «vượt ngục tinh thần»: người và trăng lặng lẽ tìm nhau.",
      "nguyen_van": [
        "Ngục trung vô tửu diệc vô hoa,",
        "Đối thử lương tiêu nại nhược hà?",
        "Nhân hướng song tiền khán minh nguyệt,",
        "Nguyệt tòng song khích khán thi gia."
      ],
      "ban_dich": [
        "Trong tù không rượu cũng không hoa,",
        "Cảnh đẹp đêm nay khó hững hờ.",
        "Người ngắm trăng soi ngoài cửa sổ,",
        "Trăng nhòm khe cửa ngắm nhà thơ."
      ],
      "ghi_chu_dich": "Bản dịch của Nam Trân (1907–1967) — đã thuộc public domain.",
      "sources": ["Ngục trung nhật ký — bản dịch Viện Văn học, NXB Văn học", "SGK Ngữ văn — NXB Giáo dục Việt Nam"]
    },
    {
      "id": "di-duong",
      "ten": "Đi đường (Tẩu lộ — Nhật ký trong tù)",
      "tac_gia": "Hồ Chí Minh",
      "thoi_ky": "1942–1943 — trên đường giải lao giữa các nhà tù Quảng Tây",
      "the_loai": "Thất ngôn tứ tuyệt chữ Hán; bản dịch Nam Trân",
      "ban_quyen": "public-domain",
      "lien_quan_tinh": [],
      "loi_binh": "Từ chuyện đường núi thành triết lý: lên đến tận cùng gian khổ sẽ «thu vào tầm mắt muôn trùng nước non».",
      "nguyen_van": [
        "Tẩu lộ tài tri tẩu lộ nan,",
        "Trùng san chi ngoại hựu trùng san.",
        "Trùng san đăng đáo cao phong hậu,",
        "Vạn lý dư đồ cố miện gian."
      ],
      "ban_dich": [
        "Đi đường mới biết gian lao,",
        "Núi cao rồi lại núi cao trập trùng.",
        "Núi cao lên đến tận cùng,",
        "Thu vào tầm mắt muôn trùng nước non."
      ],
      "ghi_chu_dich": "Bản dịch của Nam Trân (1907–1967) — đã thuộc public domain.",
      "sources": ["Ngục trung nhật ký — bản dịch Viện Văn học, NXB Văn học", "SGK Ngữ văn — NXB Giáo dục Việt Nam"]
    },
    {
      "id": "tuyen-ngon-doc-lap-trich",
      "ten": "Tuyên ngôn Độc lập (trích)",
      "tac_gia": "Hồ Chí Minh",
      "thoi_ky": "02/09/1945 — Quảng trường Ba Đình, Hà Nội",
      "the_loai": "Văn chính luận",
      "ban_quyen": "public-domain",
      "lien_quan_tinh": ["ha-noi"],
      "loi_binh": "Áng văn khai sinh nước Việt Nam Dân chủ Cộng hòa — nối «Nam quốc sơn hà» và «Bình Ngô đại cáo» thành bộ ba tuyên ngôn của dân tộc.",
      "nguyen_van": [
        "«Tất cả mọi người đều sinh ra bình đẳng. Tạo hóa cho họ những quyền không ai có thể xâm phạm được;",
        "trong những quyền ấy, có quyền được sống, quyền tự do và quyền mưu cầu hạnh phúc…»",
        "…Nước Việt Nam có quyền hưởng tự do và độc lập, và sự thực đã thành một nước tự do và độc lập.",
        "Toàn thể dân Việt Nam quyết đem tất cả tinh thần và lực lượng, tính mệnh và của cải để giữ vững quyền tự do và độc lập ấy."
      ],
      "sources": ["Hồ Chí Minh Toàn tập — NXB Chính trị quốc gia Sự thật", "tulieuvankien.dangcongsan.vn"]
    },
    {
      "id": "loi-keu-goi-toan-quoc-khang-chien-trich",
      "ten": "Lời kêu gọi toàn quốc kháng chiến (trích)",
      "tac_gia": "Hồ Chí Minh",
      "thoi_ky": "19/12/1946",
      "the_loai": "Văn chính luận",
      "ban_quyen": "public-domain",
      "lien_quan_tinh": ["ha-noi"],
      "loi_binh": "«Ai có súng dùng súng. Ai có gươm dùng gươm» — lời hịch của thời đại mới.",
      "nguyen_van": [
        "«Chúng ta muốn hòa bình, chúng ta phải nhân nhượng. Nhưng chúng ta càng nhân nhượng, thực dân Pháp càng lấn tới…",
        "Không! Chúng ta thà hy sinh tất cả, chứ nhất định không chịu mất nước, nhất định không chịu làm nô lệ…",
        "Ai có súng dùng súng. Ai có gươm dùng gươm, không có gươm thì dùng cuốc, thuổng, gậy gộc.",
        "Ai cũng phải ra sức chống thực dân Pháp cứu nước…»"
      ],
      "sources": ["Hồ Chí Minh Toàn tập — NXB Chính trị quốc gia Sự thật", "tulieuvankien.dangcongsan.vn"]
    }
  ]
}
